{
    "rho_0.0_beta_0.0001": [
        [],
        [],
        [],
        [],
        []
    ],
    "rho_0.0025_beta_0.0001": [
        [],
        [],
        [],
        [],
        []
    ],
    "rho_0.005_beta_0.0001": [
        [],
        [],
        [],
        [
            1.0
        ],
        []
    ],
    "rho_0.0075_beta_0.0001": [
        [],
        [],
        [],
        [],
        []
    ],
    "rho_0.01_beta_0.0001": [
        [],
        [],
        [],
        [],
        []
    ],
    "rho_0.0125_beta_0.0001": [
        [],
        [],
        [],
        [],
        []
    ],
    "rho_0.015_beta_0.0001": [
        [],
        [],
        [],
        [
            1.0
        ],
        [
            1.0,
            2.0,
            2.5,
            0.2
        ]
    ],
    "rho_0.0175_beta_0.0001": [
        [],
        [],
        [],
        [],
        []
    ],
    "rho_0.02_beta_0.0001": [
        [],
        [],
        [
            3.0,
            0.3333333333333333,
            1.0,
            1.0,
            2.0
        ],
        [],
        [
            2.0,
            1.0
        ]
    ],
    "rho_0.0225_beta_0.0001": [
        [],
        [],
        [],
        [],
        [
            2.0,
            0.5,
            3.0,
            0.3333333333333333
        ]
    ],
    "rho_0.025_beta_0.0001": [
        [],
        [
            1.0
        ],
        [],
        [],
        [
            1.0
        ]
    ],
    "rho_0.0275_beta_0.0001": [
        [],
        [],
        [],
        [],
        [
            2.0
        ]
    ],
    "rho_0.03_beta_0.0001": [
        [
            1.0,
            1.0
        ],
        [],
        [],
        [],
        [
            2.0
        ]
    ],
    "rho_0.04_beta_0.0001": [
        [
            1.0
        ],
        [
            2.0,
            0.5,
            2.0,
            0.5
        ],
        [
            1.0,
            1.0
        ],
        [
            6.0,
            2.1666666666666665,
            0.6923076923076923,
            0.8888888888888888,
            0.5
        ],
        []
    ],
    "rho_0.05_beta_0.0001": [
        [
            1.0
        ],
        [
            1.0,
            2.0,
            2.0,
            1.5,
            0.16666666666666666,
            1.0
        ],
        [],
        [],
        [
            1.0,
            4.0,
            1.5,
            0.6666666666666666,
            1.25,
            0.6,
            2.0,
            0.16666666666666666
        ]
    ],
    "rho_0.060000000000000005_beta_0.0001": [
        [
            2.0,
            2.0,
            0.5,
            0.5
        ],
        [
            3.0,
            3.6666666666666665,
            1.1818181818181819,
            1.1538461538461537,
            0.6666666666666666,
            0.6,
            0.6666666666666666,
            0.5,
            0.5,
            1.0
        ],
        [
            1.0
        ],
        [],
        [
            2.0,
            1.5,
            1.6666666666666667,
            0.8
        ]
    ],
    "rho_0.07_beta_0.0001": [
        [
            1.0,
            5.0,
            1.8,
            2.7777777777777777,
            1.12,
            1.0357142857142858,
            1.1724137931034482,
            0.9705882352941176,
            0.8484848484848485,
            0.6071428571428571,
            0.5294117647058824
        ],
        [],
        [
            4.0,
            1.0,
            2.0,
            1.375,
            2.1818181818181817,
            1.4583333333333333,
            1.7428571428571429,
            1.0327868852459017,
            0.873015873015873,
            1.2545454545454546,
            0.7536231884057971,
            0.75,
            0.46153846153846156,
            0.3888888888888889,
            0.42857142857142855,
            2.0,
            0.16666666666666666
        ],
        [],
        [
            1.0,
            1.0,
            5.0,
            0.8,
            0.25
        ]
    ],
    "rho_0.08000000000000002_beta_0.0001": [
        [
            1.0,
            3.0,
            3.0,
            0.4444444444444444,
            1.5
        ],
        [],
        [
            1.0
        ],
        [
            5.0,
            2.8,
            1.9285714285714286,
            1.962962962962963,
            1.9433962264150944,
            1.5533980582524272,
            1.1875,
            1.0,
            0.7842105263157895,
            0.7315436241610739,
            0.6238532110091743,
            0.5,
            0.47058823529411764,
            0.8125,
            0.15384615384615385
        ],
        [
            3.0,
            3.0,
            2.6666666666666665,
            1.0833333333333333,
            1.2307692307692308,
            0.875,
            1.3571428571428572,
            0.9736842105263158,
            0.5675675675675675,
            0.8095238095238095,
            0.11764705882352941
        ]
    ],
    "rho_0.09000000000000001_beta_0.0001": [
        [
            1.0,
            5.0,
            3.2,
            1.0,
            1.4375,
            1.0,
            0.782608695652174,
            0.5,
            0.3333333333333333,
            0.3333333333333333
        ],
        [
            7.0,
            2.0,
            1.5714285714285714,
            2.727272727272727,
            1.9333333333333333,
            1.4913793103448276,
            1.416184971098266,
            1.1306122448979592,
            0.9963898916967509,
            1.0543478260869565,
            0.8041237113402062,
            0.8803418803418803,
            0.5922330097087378,
            0.5409836065573771,
            0.5606060606060606,
            0.4594594594594595,
            0.5882352941176471,
            0.5,
            0.8
        ],
        [
            6.0,
            3.0,
            2.7777777777777777,
            1.96,
            1.7142857142857142,
            1.4880952380952381,
            1.408,
            1.0369318181818181,
            0.8821917808219178,
            0.6645962732919255,
            0.5981308411214953,
            0.5625,
            0.6111111111111112,
            0.6818181818181818,
            0.6,
            0.8333333333333334,
            0.8,
            0.25,
            0.3333333333333333,
            1.0,
            1.0
        ],
        [],
        []
    ],
    "rho_0.1_beta_0.0001": [
        [
            3.0,
            3.0,
            2.3333333333333335,
            1.9523809523809523,
            2.1707317073170733,
            1.5842696629213484,
            1.475177304964539,
            1.3028846153846154,
            1.022140221402214,
            0.9711191335740073,
            0.7843866171003717,
            0.6635071090047393,
            0.6571428571428571,
            0.391304347826087,
            0.4166666666666667,
            0.4,
            0.16666666666666666,
            1.0
        ],
        [],
        [
            2.0,
            2.0,
            1.5,
            1.8333333333333333,
            2.0,
            0.7727272727272727,
            0.9411764705882353,
            0.75,
            0.9166666666666666,
            0.2727272727272727
        ],
        [],
        [
            4.0,
            2.75,
            2.6363636363636362,
            1.9655172413793103,
            2.1403508771929824,
            1.7622950819672132,
            1.5627906976744186,
            1.6607142857142858,
            1.3620071684587813,
            1.225,
            1.0386680988184747,
            0.9917269906928645,
            0.8779979144942649,
            0.7779097387173397,
            0.6091603053435114,
            0.581453634085213,
            0.4827586206896552,
            0.4642857142857143,
            0.17307692307692307,
            0.2222222222222222
        ]
    ],
    "rho_0.0_beta_0.001": [
        [],
        [],
        [],
        [],
        []
    ],
    "rho_0.0025_beta_0.001": [
        [],
        [],
        [],
        [],
        [
            1.0
        ]
    ],
    "rho_0.005_beta_0.001": [
        [
            4.0,
            0.25,
            3.0,
            0.6666666666666666
        ],
        [
            2.0,
            1.0,
            1.5,
            0.6666666666666666,
            0.5,
            1.0
        ],
        [
            2.0,
            1.5,
            1.3333333333333333,
            0.75,
            0.6666666666666666
        ],
        [
            2.0,
            1.0,
            0.5
        ],
        [
            6.0,
            2.0,
            0.9166666666666666,
            0.36363636363636365,
            1.5,
            1.6666666666666667,
            0.8,
            1.125,
            0.2222222222222222,
            0.5
        ]
    ],
    "rho_0.0075_beta_0.001": [
        [
            7.0,
            1.4285714285714286,
            1.8,
            2.0,
            1.5277777777777777,
            1.018181818181818,
            0.9821428571428571,
            1.0727272727272728,
            1.1355932203389831,
            0.9104477611940298,
            1.0655737704918034,
            1.0153846153846153,
            1.0,
            0.7878787878787878,
            0.7115384615384616,
            0.5675675675675675,
            0.38095238095238093,
            0.5,
            0.5
        ],
        [
            2.0,
            1.0,
            0.5,
            2.0,
            2.0,
            0.5,
            0.5
        ],
        [
            2.0,
            2.5,
            1.4,
            2.0,
            1.0714285714285714,
            0.4666666666666667,
            1.4285714285714286,
            0.2
        ],
        [
            5.0,
            2.4,
            1.4166666666666667,
            1.4705882352941178,
            1.2,
            1.3,
            1.1025641025641026,
            0.7441860465116279,
            0.71875,
            0.5217391304347826,
            0.75,
            0.2222222222222222,
            1.0,
            1.0
        ],
        [
            5.0,
            2.2,
            1.8181818181818181,
            1.3,
            0.8461538461538461,
            1.5,
            1.303030303030303,
            0.4883720930232558,
            0.9047619047619048,
            0.631578947368421,
            0.5,
            0.8333333333333334,
            0.4,
            1.0,
            1.5
        ]
    ],
    "rho_0.01_beta_0.001": [
        [
            3.0,
            4.666666666666667,
            1.7857142857142858,
            1.76,
            1.0454545454545454,
            1.2173913043478262,
            0.7678571428571429,
            0.8604651162790697,
            0.4594594594594595,
            0.23529411764705882,
            0.25
        ],
        [
            2.0,
            4.0,
            1.625,
            2.3076923076923075,
            1.4666666666666666,
            0.8636363636363636,
            0.6578947368421053,
            0.72,
            0.2777777777777778,
            0.2
        ],
        [
            4.0,
            2.5,
            1.5,
            1.4,
            2.238095238095238,
            1.3617021276595744,
            0.78125,
            1.3,
            1.0769230769230769,
            0.8714285714285714,
            0.7213114754098361,
            0.45454545454545453,
            0.75,
            0.6,
            0.5555555555555556,
            0.2
        ],
        [
            2.0,
            3.5,
            3.5714285714285716,
            1.72,
            0.9534883720930233,
            1.048780487804878,
            0.9767441860465116,
            0.7142857142857143,
            0.5666666666666667,
            0.23529411764705882
        ],
        [
            1.0,
            5.0,
            2.2,
            2.4545454545454546,
            1.4074074074074074,
            0.7894736842105263,
            1.2333333333333334,
            1.2162162162162162,
            0.9111111111111111,
            0.6829268292682927,
            0.5,
            0.6428571428571429,
            1.0,
            0.8888888888888888,
            0.375,
            1.3333333333333333,
            0.5
        ]
    ],
    "rho_0.0125_beta_0.001": [
        [
            2.0,
            1.0,
            2.5,
            1.0,
            1.2,
            2.6666666666666665,
            1.0,
            0.625,
            0.3
        ],
        [
            6.0,
            1.6666666666666667,
            3.2,
            1.84375,
            1.6271186440677967,
            1.3020833333333333,
            1.28,
            1.10625,
            0.8248587570621468,
            0.7397260273972602,
            0.5277777777777778,
            0.3333333333333333,
            0.631578947368421,
            0.9166666666666666,
            0.6363636363636364,
            0.5714285714285714
        ],
        [
            3.0,
            2.6666666666666665,
            1.75,
            2.2857142857142856,
            0.78125,
            0.76,
            0.42105263157894735,
            0.5
        ],
        [
            5.0,
            1.8,
            2.3333333333333335,
            2.4285714285714284,
            1.5098039215686274,
            1.1428571428571428,
            0.7954545454545454,
            0.8285714285714286,
            0.896551724137931,
            0.3269230769230769,
            0.6470588235294118,
            0.36363636363636365
        ],
        [
            3.0,
            1.0,
            3.0,
            1.8888888888888888,
            2.0588235294117645,
            1.3142857142857143,
            1.065217391304348,
            0.9387755102040817,
            0.43478260869565216,
            0.8,
            0.4375,
            0.14285714285714285,
            1.0
        ]
    ],
    "rho_0.015_beta_0.001": [
        [
            6.0,
            3.6666666666666665,
            2.227272727272727,
            2.489795918367347,
            1.8688524590163935,
            1.513157894736842,
            1.3217391304347825,
            1.3574561403508771,
            1.1324717285945072,
            1.1982881597717547,
            1.042857142857143,
            1.0319634703196348,
            0.964562569213732,
            0.9058553386911596,
            0.7984790874524715,
            0.7428571428571429,
            0.6346153846153846,
            0.6397306397306397,
            0.6526315789473685,
            0.5806451612903226,
            0.4027777777777778,
            0.1724137931034483,
            0.2
        ],
        [
            5.0,
            3.6,
            3.2777777777777777,
            2.1186440677966103,
            1.592,
            1.4020100502512562,
            1.1863799283154122,
            1.2356495468277946,
            1.17359413202934,
            1.09375,
            0.9542857142857143,
            0.8522954091816367,
            0.7798594847775175,
            0.7657657657657657,
            0.6509803921568628,
            0.6024096385542169,
            0.5,
            0.58,
            0.5172413793103449,
            1.0666666666666667,
            0.5
        ],
        [
            3.0,
            3.6666666666666665,
            2.3636363636363638,
            1.8076923076923077,
            1.872340425531915,
            1.5681818181818181,
            1.4130434782608696,
            1.235897435897436,
            1.1742738589211619,
            1.017667844522968,
            1.1597222222222223,
            0.8173652694610778,
            0.7875457875457875,
            0.7534883720930232,
            0.7962962962962963,
            0.5813953488372093,
            0.38666666666666666,
            0.27586206896551724,
            0.125
        ],
        [
            5.0,
            5.2,
            2.9615384615384617,
            2.012987012987013,
            1.6903225806451614,
            1.5305343511450382,
            1.3241895261845387,
            1.2862523540489643,
            1.2093704245973647,
            1.1138014527845037,
            1.0217391304347827,
            0.9191489361702128,
            0.7881944444444444,
            0.6490455212922174,
            0.5520361990950227,
            0.569672131147541,
            0.6115107913669064,
            0.5176470588235295,
            0.4772727272727273,
            0.23809523809523808
        ],
        [
            1.0,
            14.0,
            2.5,
            2.5142857142857142,
            1.8977272727272727,
            1.622754491017964,
            1.3431734317343174,
            1.2774725274725274,
            1.3010752688172043,
            1.0710743801652893,
            0.9922839506172839,
            0.9626749611197511,
            0.9321486268174475,
            0.8388214904679376,
            0.7128099173553719,
            0.7304347826086957,
            0.5674603174603174,
            0.5384615384615384,
            0.6753246753246753,
            0.6538461538461539,
            0.6470588235294118,
            0.45454545454545453,
            0.5,
            0.8
        ]
    ],
    "rho_0.0175_beta_0.001": [
        [
            1.0,
            5.0,
            3.6,
            3.0,
            1.8518518518518519,
            1.36,
            1.1985294117647058,
            1.049079754601227,
            0.8830409356725146,
            0.7682119205298014,
            0.6724137931034483,
            0.5769230769230769,
            0.4444444444444444,
            0.55,
            0.36363636363636365,
            1.5,
            0.3333333333333333
        ],
        [
            5.0,
            4.2,
            2.761904761904762,
            1.5862068965517242,
            1.434782608695652,
            1.696969696969697,
            1.53125,
            1.434402332361516,
            1.1341463414634145,
            1.1756272401433692,
            1.1189024390243902,
            0.9713896457765667,
            0.9915848527349228,
            1.0537482319660538,
            0.9906040268456375,
            0.9661246612466124,
            0.8415147265077139,
            0.8083333333333333,
            0.7298969072164948,
            0.7429378531073446,
            0.8022813688212928,
            0.7061611374407583,
            0.6375838926174496,
            0.5157894736842106,
            0.5416666666666666,
            0.6129032258064516,
            0.47368421052631576,
            0.3333333333333333
        ],
        [
            2.0,
            3.0,
            4.166666666666667,
            1.96,
            2.0816326530612246,
            1.6470588235294117,
            1.5952380952380953,
            1.1902985074626866,
            1.141065830721003,
            1.0027472527472527,
            0.8493150684931506,
            0.8580645161290322,
            0.6428571428571429,
            0.7602339181286549,
            0.6538461538461539,
            0.6,
            0.5490196078431373,
            0.39285714285714285,
            0.36363636363636365
        ],
        [
            7.0,
            3.4285714285714284,
            2.625,
            1.9682539682539681,
            1.6209677419354838,
            1.7064676616915422,
            1.553935860058309,
            1.3789868667917449,
            1.3061224489795917,
            1.225,
            1.1327659574468085,
            1.0074906367041199,
            0.9524163568773234,
            0.8828125,
            0.8131089459698848,
            0.7926167209554832,
            0.8440492476060192,
            0.7990275526742301,
            0.7484787018255578,
            0.6775067750677507,
            0.696,
            0.45977011494252873,
            0.5625,
            0.3111111111111111
        ],
        [
            5.0,
            4.8,
            3.375,
            1.9506172839506173,
            1.9113924050632911,
            1.4503311258278146,
            1.417808219178082,
            1.183574879227053,
            1.220408163265306,
            1.060200668896321,
            0.9474237644584648,
            0.9456159822419534,
            0.8720657276995305,
            0.8465679676985195,
            0.7404458598726115,
            0.6008583690987125,
            0.6285714285714286,
            0.5511363636363636,
            0.41237113402061853,
            0.45,
            0.2222222222222222
        ]
    ],
    "rho_0.02_beta_0.001": [
        [
            4.0,
            5.0,
            3.15,
            2.238095238095238,
            1.49645390070922,
            1.6066350710900474,
            1.4277286135693215,
            1.3822314049586777,
            1.2645739910313902,
            1.0732860520094563,
            1.0848017621145374,
            0.9532994923857868,
            0.7859424920127795,
            0.7588075880758808,
            0.7071428571428572,
            0.6590909090909091,
            0.6206896551724138,
            0.4444444444444444,
            0.4583333333333333,
            0.2727272727272727,
            0.4444444444444444
        ],
        [
            11.0,
            1.9090909090909092,
            2.142857142857143,
            2.1555555555555554,
            2.0721649484536084,
            1.955223880597015,
            1.618320610687023,
            1.4465408805031446,
            1.2633297062023938,
            1.1551724137931034,
            1.1446681580909768,
            1.0435630689206763,
            0.9631710362047441,
            0.9174725983236621,
            0.9161971830985915,
            0.8784615384615385,
            0.8181019332161688,
            0.7890204520990313,
            0.6903137789904502,
            0.6522593320235757,
            0.6295180722891566,
            0.3014354066985646,
            0.47619047619047616,
            0.23333333333333334,
            0.2857142857142857,
            1.0,
            0.5
        ],
        [
            9.0,
            4.111111111111111,
            2.4594594594594597,
            2.318681318681319,
            1.5971563981042654,
            1.3798219584569733,
            1.2795698924731183,
            1.2285714285714286,
            1.1956224350205198,
            1.1807780320366132,
            1.1930164888457808,
            1.1007311129163282,
            1.0856088560885608,
            1.008849557522124,
            0.9371621621621622,
            0.8898488120950324,
            0.8745954692556634,
            0.8011100832562442,
            0.6697459584295612,
            0.6379310344827587,
            0.5918918918918918,
            0.4748858447488584,
            0.3942307692307692,
            0.43902439024390244,
            0.4444444444444444,
            0.125
        ],
        [
            2.0,
            4.0,
            2.625,
            2.3333333333333335,
            2.326530612244898,
            1.9649122807017543,
            1.8214285714285714,
            1.428921568627451,
            1.183533447684391,
            1.063768115942029,
            1.0463215258855585,
            0.9361979166666666,
            0.8553546592489569,
            0.775609756097561,
            0.7211740041928721,
            0.7296511627906976,
            0.6733067729083665,
            0.5384615384615384,
            0.3516483516483517,
            0.3125,
            0.3
        ],
        [
            3.0,
            7.333333333333333,
            2.5,
            2.581818181818182,
            1.8943661971830985,
            1.6022304832713754,
            1.408352668213457,
            1.172981878088962,
            1.2401685393258426,
            1.2083805209513023,
            1.1630740393626993,
            1.0983870967741935,
            1.1085840058694056,
            1.0696286472148542,
            0.9548267326732673,
            0.863075924724205,
            0.7902255639097744,
            0.7971428571428572,
            0.7016706443914081,
            0.6751700680272109,
            0.5984848484848485,
            0.6329113924050633,
            0.7133333333333334,
            0.6915887850467289,
            0.5540540540540541,
            0.425,
            0.2631578947368421,
            0.2
        ]
    ],
    "rho_0.0225_beta_0.001": [
        [
            4.0,
            4.0,
            3.1875,
            2.5294117647058822,
            2.124031007751938,
            1.551094890510949,
            1.5741176470588236,
            1.3886397608370702,
            1.2734122712594187,
            1.1496196111580728,
            1.0389705882352942,
            0.9886765746638358,
            0.9355762347888332,
            0.8223583460949464,
            0.6229050279329609,
            0.6831091180866966,
            0.6586433260393874,
            0.5548172757475083,
            0.49101796407185627,
            0.3902439024390244,
            0.28125,
            0.1111111111111111
        ],
        [
            5.0,
            3.4,
            3.823529411764706,
            2.4153846153846152,
            1.9490445859872612,
            1.6830065359477124,
            1.5067961165048545,
            1.4046391752577319,
            1.2321100917431194,
            1.2457185405807893,
            1.0952095808383233,
            1.0306010928961749,
            0.9597457627118644,
            0.9955801104972376,
            0.9855955678670361,
            0.8996051889452905,
            0.809136420525657,
            0.756003098373354,
            0.6635897435897435,
            0.6486068111455109,
            0.4785714285714286,
            0.417910447761194,
            0.36904761904761907,
            0.25806451612903225,
            0.625,
            0.4
        ],
        [],
        [],
        [
            5.0,
            5.0,
            2.96,
            2.1216216216216215,
            1.7197452229299364,
            1.488888888888889,
            1.390547263681592,
            1.424731182795699,
            1.349246231155779,
            1.2085661080074488,
            1.1810477657935285,
            1.0437051532941943,
            1.1040100250626566,
            1.0384833050367854,
            1.0572831423895255,
            0.96900826446281,
            0.8814102564102564,
            0.8837772397094431,
            0.7731958762886598,
            0.7201062887511072,
            0.7002457002457002,
            0.6566901408450704,
            0.5294117647058824,
            0.40703517587939697,
            0.38271604938271603,
            0.5483870967741935,
            0.47058823529411764,
            0.5,
            0.25
        ]
    ],
    "rho_0.025_beta_0.001": [
        [
            2.0,
            3.5,
            3.7142857142857144,
            3.1538461538461537,
            2.3902439024390243,
            1.969387755102041,
            1.6062176165803108,
            1.429032258064516,
            1.1862302483069977,
            1.2388201712654614,
            1.1083781706379707,
            1.1019417475728155,
            1.1190926275992439,
            1.0918309859154929,
            1.0180785123966942,
            0.9614408929477423,
            0.9304164470216131,
            0.9563492063492064,
            0.8320474777448071,
            0.8209700427960057,
            0.6909722222222222,
            0.602996254681648,
            0.6128364389233955,
            0.5254237288135594,
            0.49032258064516127,
            0.3684210526315789,
            0.39285714285714285,
            0.5454545454545454,
            0.5
        ],
        [
            2.0,
            2.0,
            3.75,
            4.2,
            2.238095238095238,
            1.6595744680851063,
            1.4273504273504274,
            1.098802395209581,
            1.1362397820163488,
            0.9088729016786571,
            0.9920844327176781,
            0.8191489361702128,
            0.6168831168831169,
            0.6842105263157895,
            0.6384615384615384,
            0.42168674698795183,
            0.45714285714285713,
            0.25
        ],
        [
            2.0,
            5.0,
            4.7,
            2.6595744680851063,
            2.256,
            1.6134751773049645,
            1.312087912087912,
            1.407035175879397,
            1.2607142857142857,
            1.145420207743154,
            0.9785655399835119,
            0.9056444818871103,
            0.772093023255814,
            0.6566265060240963,
            0.6330275229357798,
            0.5855072463768116,
            0.5148514851485149,
            0.5480769230769231,
            0.5789473684210527,
            0.6060606060606061,
            0.55,
            0.45454545454545453,
            0.2
        ],
        [
            6.0,
            3.1666666666666665,
            4.0,
            2.6315789473684212,
            1.84,
            1.559782608695652,
            1.4547038327526132,
            1.3736526946107785,
            1.2397558849171753,
            1.1715893108298172,
            1.0744744744744745,
            0.9670206819452208,
            1.0028918449971083,
            0.8860103626943006,
            0.8464541314248536,
            0.6960859554873369,
            0.6291390728476821,
            0.6543859649122807,
            0.6112600536193029,
            0.4605263157894737,
            0.44761904761904764,
            0.48936170212765956,
            0.34782608695652173,
            0.875,
            0.14285714285714285
        ],
        [
            8.0,
            3.0,
            3.3333333333333335,
            2.2875,
            1.9180327868852458,
            1.5327635327635327,
            1.328996282527881,
            1.1986013986013986,
            1.2695449241540258,
            1.2564338235294117,
            1.0899780541331383,
            1.1140939597315436,
            1.0867992766726944,
            1.029966703662597,
            0.9730312837108953,
            0.9084350721420644,
            0.8337408312958435,
            0.7375,
            0.7307307307307307,
            0.5512995896032832,
            0.5771144278606966,
            0.5732758620689655,
            0.5263157894736842,
            0.5,
            0.5714285714285714,
            0.631578947368421,
            0.25,
            0.3333333333333333
        ]
    ],
    "rho_0.0275_beta_0.001": [
        [
            6.0,
            5.0,
            2.3333333333333335,
            2.5142857142857142,
            2.0625,
            1.674931129476584,
            1.5411184210526316,
            1.303094983991462,
            1.339066339066339,
            1.2311926605504586,
            1.165424739195231,
            1.0935098206660974,
            1.0405616224648986,
            1.0104790419161678,
            0.9037749814951888,
            0.8246116107931316,
            0.8072348860257681,
            0.7575384615384615,
            0.6955465587044535,
            0.6336056009334889,
            0.5966850828729282,
            0.5696594427244582,
            0.5543478260869565,
            0.39603960396039606,
            0.125,
            0.4
        ],
        [
            3.0,
            5.0,
            3.3333333333333335,
            2.6,
            2.476923076923077,
            1.7422360248447204,
            1.463458110516934,
            1.3252131546894033,
            1.2426470588235294,
            1.1738165680473374,
            1.1008191556395714,
            1.2217765042979942,
            1.147610121836926,
            1.0932134096484056,
            0.9726386806596702,
            0.9342813220599538,
            0.8412176059234883,
            0.8005879470847623,
            0.7509225092250923,
            0.619281045751634,
            0.6434210526315789,
            0.5439672801635992,
            0.42105263157894735,
            0.5043478260869565,
            0.42105263157894735,
            0.4583333333333333,
            0.2727272727272727,
            0.3333333333333333
        ],
        [
            6.0,
            3.6666666666666665,
            3.3636363636363638,
            2.1621621621621623,
            2.0875,
            1.874251497005988,
            1.6150159744408945,
            1.4193867457962412,
            1.2710801393728224,
            1.1513157894736843,
            1.0885714285714285,
            1.0661120840630474,
            1.009046052631579,
            0.9204406364749081,
            0.8874113475177305,
            0.8210894552723638,
            0.7681071211199026,
            0.7666666666666667,
            0.6563146997929606,
            0.5622047244094488,
            0.6376404494382022,
            0.6283185840707964,
            0.5673758865248227,
            0.41975308641975306,
            0.3235294117647059,
            0.18181818181818182
        ],
        [
            2.0,
            3.5,
            3.7142857142857144,
            4.346153846153846,
            2.433628318584071,
            1.9672727272727273,
            1.4510166358595193,
            1.4012738853503184,
            1.2472727272727273,
            1.1494169096209912,
            1.1636017755231451,
            1.0692098092643052,
            0.9704383282364933,
            0.9716386554621849,
            0.9345945945945946,
            0.802547770700637,
            0.7417027417027418,
            0.6159068865179438,
            0.49763779527559054,
            0.5079365079365079,
            0.5031446540880503,
            0.475,
            0.5,
            0.42105263157894735,
            0.25
        ],
        []
    ],
    "rho_0.03_beta_0.001": [
        [
            9.0,
            4.222222222222222,
            2.3947368421052633,
            2.120879120879121,
            2.010362694300518,
            1.7190721649484537,
            1.502248875562219,
            1.31437125748503,
            1.222475322703113,
            1.197139303482587,
            1.1364107883817427,
            1.1293418647166362,
            1.0734279918864098,
            1.0430676237249716,
            0.9163649529326575,
            0.9165017807677087,
            0.7989668532070598,
            0.7617504051863857,
            0.7659123055162659,
            0.7442289935364728,
            0.8099378881987578,
            0.7987711213517665,
            0.6711538461538461,
            0.7306590257879656,
            0.6666666666666666,
            0.711764705882353,
            0.5537190082644629,
            0.4925373134328358,
            0.2727272727272727,
            0.2222222222222222
        ],
        [
            4.0,
            4.5,
            2.7777777777777777,
            2.74,
            2.065693430656934,
            1.862190812720848,
            1.7324478178368121,
            1.3274917853231105,
            1.2896039603960396,
            1.1599488163787588,
            1.1286581998895637,
            1.1200391964723175,
            1.068831168831169,
            1.086234817813765,
            1.005963473723444,
            0.902746844840386,
            0.8261943986820428,
            0.8247628557164254,
            0.7680193821926106,
            0.7241106719367589,
            0.6980306345733042,
            0.6206896551724138,
            0.5714285714285714,
            0.4469026548672566,
            0.8316831683168316,
            0.7654320987654321,
            0.6349206349206349,
            0.5384615384615384,
            0.38095238095238093,
            0.375
        ],
        [
            9.0,
            5.222222222222222,
            2.9148936170212765,
            2.3649635036496353,
            1.8179012345679013,
            1.6298811544991512,
            1.3697916666666667,
            1.2334600760456274,
            1.1972872996300863,
            1.1029866117404736,
            1.1405885100420365,
            1.0836065573770493,
            1.0480514566780175,
            0.9996391194514616,
            0.9065319379285457,
            0.8398887564560985,
            0.7784629981024668,
            0.7681513117754728,
            0.6923076923076923,
            0.6929223744292238,
            0.6699507389162561,
            0.6699266503667481,
            0.6360294117647058,
            0.5542857142857143,
            0.5463917525773195,
            0.6981132075471698,
            0.3783783783783784,
            0.2857142857142857,
            0.5
        ],
        [
            11.0,
            3.8181818181818183,
            3.4523809523809526,
            2.103448275862069,
            1.8,
            1.5610200364298725,
            1.3593932322053675,
            1.2523605150214592,
            1.1802604523646334,
            1.1574665891923301,
            1.1160220994475138,
            1.081605049594229,
            1.0859407592824364,
            1.0065284178187404,
            0.9226942212016839,
            0.9074688796680498,
            0.8292124542124543,
            0.7178354500276091,
            0.7157164869029276,
            0.6545064377682404,
            0.5930807248764415,
            0.6657458563535912,
            0.5975103734439834,
            0.5902777777777778,
            0.5058823529411764,
            0.6744186046511628,
            0.1724137931034483
        ],
        []
    ],
    "rho_0.04_beta_0.001": [
        [
            13.0,
            4.3076923076923075,
            2.7857142857142856,
            2.3205128205128207,
            1.8922651933701657,
            1.6948905109489052,
            1.4298018949181739,
            1.2662650602409637,
            1.1841103710751666,
            1.190112540192926,
            1.114527027027027,
            1.0990580370707992,
            1.0433581883457608,
            1.0196599362380447,
            0.9566692769511876,
            0.867506159321106,
            0.7871130764371447,
            0.7203696263559662,
            0.6965978806469604,
            0.5544871794871795,
            0.5122302158273381,
            0.37815126050420167,
            0.48148148148148145,
            0.38461538461538464,
            0.56,
            0.6428571428571429,
            0.2222222222222222
        ],
        [
            3.0,
            7.333333333333333,
            3.6363636363636362,
            2.9125,
            2.124463519313305,
            1.7575757575757576,
            1.5390804597701149,
            1.3061986557132188,
            1.2625858123569793,
            1.245129134571817,
            1.1598107025846378,
            1.0546825895663106,
            1.064102564102564,
            1.0019607843137255,
            0.9443667878110148,
            0.8666468666468666,
            0.8574854402192532,
            0.855026031237485,
            0.8003757632691404,
            0.7220259128386337,
            0.7072771872444807,
            0.5335648148148148,
            0.5869565217391305,
            0.5625,
            0.6274509803921569,
            0.84375,
            0.55,
            0.6818181818181818,
            0.3448275862068966,
            0.4
        ],
        [
            4.0,
            6.25,
            3.16,
            2.4430379746835444,
            2.1917098445595853,
            1.8108747044917257,
            1.3890339425587468,
            1.3195488721804511,
            1.3682336182336183,
            1.1910463300364393,
            1.1986001749781277,
            1.1372262773722628,
            1.0739312118289939,
            1.0456989247311828,
            1.0417142857142858,
            0.981897970378497,
            0.8995804195804196,
            0.8200186509170034,
            0.7691723614274867,
            0.7183168316831683,
            0.6493055555555556,
            0.6648992576882291,
            0.6528,
            0.515970515970516,
            0.5904761904761905,
            0.4435483870967742,
            0.42592592592592593,
            0.4583333333333333,
            0.36363636363636365
        ],
        [
            10.0,
            4.0,
            3.525,
            2.2127659574468086,
            2.0576923076923075,
            1.6744548286604362,
            1.4595348837209303,
            1.2982791586998088,
            1.1832023575638506,
            1.1685346616853467,
            1.152096659559346,
            1.0923929781336619,
            1.0081874647092037,
            0.9349593495934959,
            0.9345738295318127,
            0.9088282504012841,
            0.8635235732009926,
            0.8143268834911486,
            0.800302571860817,
            0.7585551330798479,
            0.7412353923205343,
            0.6024774774774775,
            0.5196261682242991,
            0.5345454545454545,
            0.4863013698630137,
            0.42857142857142855,
            0.3333333333333333,
            0.4,
            0.25
        ],
        [
            8.0,
            4.5,
            3.1944444444444446,
            2.8260869565217392,
            2.187692307692308,
            1.7313642756680732,
            1.3793663688058488,
            1.309776207302709,
            1.1659172661870503,
            1.1045524691358024,
            1.096301465457083,
            1.0895760280522793,
            1.040923706518562,
            0.9949509116409537,
            0.9534292972057579,
            0.8677514792899408,
            0.8407534246575342,
            0.7570322054626988,
            0.7163616792249731,
            0.6920754716981132,
            0.6510869565217391,
            0.6130653266331658,
            0.6328767123287671,
            0.6347826086956522,
            0.6413793103448275,
            0.5760869565217391,
            0.3333333333333333,
            0.3333333333333333,
            0.6666666666666666,
            0.25
        ]
    ],
    "rho_0.05_beta_0.001": [
        [
            12.0,
            4.666666666666667,
            2.9285714285714284,
            2.475609756097561,
            2.0665024630541873,
            1.6531585220500595,
            1.5025234318673395,
            1.3862763915547025,
            1.2534626038781163,
            1.1387506909894969,
            1.0838599902771027,
            1.013027852650494,
            1.017501107665042,
            0.9703832752613241,
            0.9269827005167378,
            0.8493084202863382,
            0.8180515759312321,
            0.7769961308476961,
            0.6951992753623188,
            0.6245110821382008,
            0.5683003128258602,
            0.4900181488203267,
            0.48134328358208955,
            0.34108527131782945,
            0.29545454545454547,
            0.38461538461538464,
            0.2,
            1.0
        ],
        [
            3.0,
            6.666666666666667,
            4.9,
            3.173469387755102,
            2.167202572347267,
            1.728486646884273,
            1.5356223175965664,
            1.3236444941307994,
            1.2792564427545416,
            1.2093100033014197,
            1.157592339261286,
            1.0695199810829983,
            1.035658914728682,
            1.015825491873396,
            0.9554288128432615,
            0.9095132743362832,
            0.8216902784562775,
            0.7304606240713224,
            0.6543159609120521,
            0.6442367601246106,
            0.5793573515092503,
            0.5117845117845118,
            0.6611842105263158,
            0.6984924623115578,
            0.5179856115107914,
            0.647887323943662,
            0.4782608695652174,
            0.7272727272727273,
            0.5625,
            0.1111111111111111
        ],
        [
            6.0,
            4.833333333333333,
            3.0689655172413794,
            2.8202247191011236,
            2.3386454183266934,
            1.9114139693356047,
            1.5338680926916222,
            1.4113887274840209,
            1.2441333882256072,
            1.1906653426017875,
            1.0927318295739348,
            1.111791730474732,
            1.0794489092996555,
            1.0242966751918159,
            0.9599666388657214,
            0.8998909487459106,
            0.824501701507049,
            0.7405437352245863,
            0.6884261113336003,
            0.6612244897959184,
            0.6186291739894552,
            0.6310541310541311,
            0.5530474040632054,
            0.5877551020408164,
            0.3888888888888889,
            0.42857142857142855,
            0.4583333333333333
        ],
        [
            4.0,
            6.75,
            3.1481481481481484,
            2.8823529411764706,
            2.012244897959184,
            1.7748478701825559,
            1.672,
            1.3725222146274778,
            1.282370517928287,
            1.2171717171717171,
            1.2177522349936143,
            1.1066176470588236,
            1.1121406509859824,
            1.0569471205309355,
            0.9723014256619145,
            0.9240108854929873,
            0.8762769580022701,
            0.7617076326002588,
            0.7158432708688245,
            0.6601618277010948,
            0.6186685962373372,
            0.5686274509803921,
            0.48775510204081635,
            0.4641350210970464,
            0.36036036036036034,
            0.3023255813953488,
            0.6153846153846154,
            0.25
        ],
        [
            7.0,
            6.428571428571429,
            3.2444444444444445,
            2.5547945205479454,
            1.8498659517426272,
            1.6782608695652175,
            1.4533678756476685,
            1.3814616755793225,
            1.2925989672977625,
            1.1628989361702127,
            1.1581807780320366,
            1.126826851622492,
            1.076686442540101,
            0.9901900674432863,
            0.8798425523099234,
            0.8794159208666981,
            0.7908969210174029,
            0.7835365853658537,
            0.7660590277777778,
            0.7258338044092708,
            0.6747269890795632,
            0.651270207852194,
            0.6826241134751773,
            0.5260416666666666,
            0.5742574257425742,
            0.5603448275862069,
            0.3076923076923077,
            0.65,
            0.38461538461538464
        ]
    ],
    "rho_0.060000000000000005_beta_0.001": [
        [
            8.0,
            5.0,
            3.15,
            2.634920634920635,
            1.855421686746988,
            1.780844155844156,
            1.5961713764813126,
            1.4437464306110794,
            1.360759493670886,
            1.2864204710671707,
            1.1851265822784811,
            1.1429115853658536,
            1.042063094641963,
            0.9571084337349398,
            0.8923880094307848,
            0.8618482966309053,
            0.8195175438596491,
            0.7575838926174496,
            0.7332149200710479,
            0.6925329428989752,
            0.6296296296296297,
            0.5986622073578596,
            0.5910780669144982,
            0.48417721518987344,
            0.4645161290322581,
            0.3055555555555556,
            0.18181818181818182,
            0.25
        ],
        [
            5.0,
            4.8,
            4.541666666666667,
            3.091743119266055,
            2.27893175074184,
            1.8580729166666667,
            1.545199719691661,
            1.32562358276644,
            1.2904550119739993,
            1.2214854111405835,
            1.1005659555942533,
            1.1005154639175259,
            1.0483405483405484,
            0.9672131147540983,
            0.9322730521801287,
            0.9069005397070162,
            0.8284011070896317,
            0.7526383526383527,
            0.6824093086926762,
            0.6498993963782697,
            0.6088303640588691,
            0.5655526992287918,
            0.4153498871331828,
            0.4098360655737705,
            0.3783783783783784,
            0.17857142857142858
        ],
        [
            13.0,
            5.461538461538462,
            2.7183098591549295,
            2.0725388601036268,
            1.9025,
            1.6084099868593955,
            1.5049019607843137,
            1.3718783930510314,
            1.3157894736842106,
            1.2160048134777377,
            1.0913592473384501,
            1.1139872842870118,
            1.0424230063226596,
            1.003523194362889,
            0.9834081592816709,
            0.9540207006369427,
            0.9015294364131573,
            0.8290058479532164,
            0.7761570827489481,
            0.7336701551786359,
            0.7095660749506904,
            0.603905160390516,
            0.593279258400927,
            0.5118577075098815,
            0.51171875,
            0.3409090909090909,
            0.27906976744186046,
            0.6,
            0.6666666666666666,
            0.3333333333333333
        ],
        [
            13.0,
            5.153846153846154,
            2.985074626865672,
            2.455,
            1.9042769857433808,
            1.6459893048128342,
            1.3703703703703705,
            1.2912713472485768,
            1.240910760190966,
            1.2229789754219722,
            1.1127510283087345,
            1.120888695273361,
            1.066083576287658,
            1.0244704163623082,
            0.9751608291636884,
            0.8944373049384983,
            0.8330592105263158,
            0.7521091811414392,
            0.7031404958677686,
            0.6826741996233522,
            0.6703524533517623,
            0.6190965092402464,
            0.6320132013201321,
            0.5593667546174143,
            0.5258215962441315,
            0.35714285714285715,
            0.175,
            0.14285714285714285
        ],
        [
            9.0,
            4.777777777777778,
            3.0,
            2.5968992248062017,
            1.9970149253731344,
            1.704035874439462,
            1.4982456140350877,
            1.3518735362997658,
            1.3365093113902122,
            1.2475696694750487,
            1.2323888744476215,
            1.131434599156118,
            1.0810911808669657,
            1.0608365019011408,
            0.9693661398077237,
            0.8989711587114184,
            0.844168079894479,
            0.7335269153450972,
            0.6560098370734706,
            0.6817334575955266,
            0.6027586206896551,
            0.5970319634703196,
            0.45419103313840153,
            0.4388185654008439,
            0.4368932038834951,
            0.4,
            0.3888888888888889,
            0.14285714285714285
        ]
    ],
    "rho_0.07_beta_0.001": [
        [
            9.0,
            6.666666666666667,
            3.316666666666667,
            2.5527638190954773,
            2.1535433070866143,
            1.6005484460694699,
            1.42,
            1.3774647887323943,
            1.3064563248612329,
            1.2140939597315437,
            1.1767955801104972,
            1.1004236623254355,
            1.0586720091585575,
            0.9668381158635625,
            0.877141252457175,
            0.8437700706486834,
            0.7536287242169595,
            0.6998985286656519,
            0.6426229508196721,
            0.5862068965517241,
            0.6044921875,
            0.5475040257648953,
            0.5253731343283582,
            0.4198895027624309,
            0.4805194805194805,
            0.3611111111111111,
            0.5384615384615384
        ],
        [
            11.0,
            5.454545454545454,
            3.066666666666667,
            2.5,
            1.8021739130434782,
            1.7840772014475272,
            1.5469912102772143,
            1.3763111888111887,
            1.2899333121625913,
            1.2570795370598375,
            1.1848871442590776,
            1.152382528127068,
            1.0526542943461372,
            0.9954794520547945,
            0.9392600773053562,
            0.8386099249006037,
            0.7650167341905936,
            0.6939764597276714,
            0.6656626506024096,
            0.6289592760180995,
            0.5907643312101911,
            0.48517520215633425,
            0.36694677871148457,
            0.38636363636363635,
            0.3333333333333333,
            0.35294117647058826,
            0.3333333333333333,
            0.5,
            1.0
        ],
        [
            3.0,
            8.0,
            3.9583333333333335,
            3.463157894736842,
            2.7142857142857144,
            1.9708846584546473,
            1.6210227272727273,
            1.3459516298633019,
            1.1917165928627247,
            1.162363238512035,
            1.1532379518072289,
            1.102669068282299,
            1.030325553738665,
            0.9832684263666522,
            0.8944419873212442,
            0.8330305532617671,
            0.7869964100518548,
            0.7578814627994955,
            0.7364909939959974,
            0.6648526077097505,
            0.5650988411724608,
            0.5321212121212121,
            0.44719101123595506,
            0.38190954773869346,
            0.34210526315789475,
            0.34615384615384615,
            0.2222222222222222,
            1.0
        ],
        [
            10.0,
            4.9,
            2.9591836734693877,
            2.8758620689655174,
            2.1079136690647484,
            1.7781569965870307,
            1.5873320537428024,
            1.3417976622329706,
            1.26953125,
            1.2252786341000712,
            1.1659253529298008,
            1.1168831168831168,
            1.0445241296877334,
            0.9921180854112926,
            0.9228323699421965,
            0.8306311978592791,
            0.7970381621416366,
            0.7607449856733525,
            0.7089246294544308,
            0.6929941990182954,
            0.5956213779781069,
            0.5449620801733478,
            0.49798387096774194,
            0.4796747967479675,
            0.41025641025641024,
            0.375,
            1.2222222222222223,
            0.9090909090909091,
            0.55,
            0.45454545454545453,
            0.4,
            0.5
        ],
        [
            5.0,
            6.4,
            4.5,
            2.8125,
            2.5382716049382714,
            1.740272373540856,
            1.4717719396310789,
            1.3554880364603115,
            1.216587279349958,
            1.1810642709053214,
            1.1504977552215498,
            1.1119605844376486,
            1.056771231828615,
            1.0041943881978594,
            0.938710610002891,
            0.8633271490414347,
            0.795848989085704,
            0.7332584269662922,
            0.6357798165137615,
            0.5648596321393998,
            0.5337954939341422,
            0.5162866449511401,
            0.4952681388012618,
            0.44871794871794873,
            0.44285714285714284,
            0.3,
            0.3,
            0.3333333333333333,
            1.0
        ]
    ],
    "rho_0.08000000000000002_beta_0.001": [
        [
            10.0,
            5.7,
            3.789473684210526,
            2.736111111111111,
            2.1150592216582065,
            1.836,
            1.582570806100218,
            1.4008810572687225,
            1.2549135220125787,
            1.1556670324502274,
            1.1462020147018785,
            1.0580277678889285,
            0.9620410002252759,
            0.8769248853885035,
            0.8142818719741797,
            0.7503295978905735,
            0.7092715231788079,
            0.6748984057517975,
            0.6499077490774908,
            0.6178747361013371,
            0.5933940774487472,
            0.5562015503875969,
            0.4359861591695502,
            0.421875,
            0.6415094339622641,
            0.35294117647058826,
            0.5833333333333334
        ],
        [
            10.0,
            7.1,
            3.5774647887323945,
            2.8149606299212597,
            2.0475524475524476,
            1.6762295081967213,
            1.5071341214838974,
            1.3506353068396864,
            1.2165031043460846,
            1.1421512106736946,
            1.109393063583815,
            1.0424281984334203,
            1.0126804770872568,
            0.9304261398931545,
            0.8694014794889038,
            0.8177034973692355,
            0.7583396512509477,
            0.6661642803315749,
            0.5957767722473605,
            0.5698992443324937,
            0.5243362831858407,
            0.4087136929460581,
            0.3163265306122449,
            0.23333333333333334,
            0.1875
        ],
        [
            4.0,
            9.75,
            4.153846153846154,
            2.7160493827160495,
            2.340909090909091,
            1.692233009708738,
            1.5060240963855422,
            1.3300267073636016,
            1.2587392550143266,
            1.2445305378304468,
            1.1980234260614935,
            1.1296154435422092,
            1.095968508212298,
            0.9858156028368794,
            0.8948834853090172,
            0.9019081272084806,
            0.8439170072304307,
            0.7676711309523809,
            0.7140077821011673,
            0.6824531516183986,
            0.6251881585549423,
            0.49396621078037006,
            0.4444444444444444,
            0.47619047619047616,
            0.5,
            0.3230769230769231,
            0.38095238095238093,
            0.125
        ],
        [
            10.0,
            7.1,
            3.591549295774648,
            2.7372549019607844,
            2.103151862464183,
            1.7574931880108993,
            1.4713178294573643,
            1.3242887249736566,
            1.2519402985074626,
            1.1692944736422997,
            1.1263945578231294,
            1.0625151441725225,
            0.980034227039361,
            0.9134604139866682,
            0.8068631202959561,
            0.7350941009014709,
            0.6705301566859841,
            0.6276150627615062,
            0.572452636968766,
            0.592128801431127,
            0.5742424242424242,
            0.46965699208443273,
            0.4777777777777778,
            0.4069767441860465,
            0.17142857142857143,
            0.3333333333333333
        ],
        [
            16.0,
            4.5,
            2.9027777777777777,
            2.124401913875598,
            1.9211711711711712,
            1.656506447831184,
            1.6234961075725407,
            1.467741935483871,
            1.3163992869875223,
            1.2782039711191335,
            1.16292631206927,
            1.1106881851400732,
            1.0573274676931537,
            1.0384866275277234,
            0.9852421796165489,
            0.9017467248908297,
            0.8129271070615034,
            0.7419468403450097,
            0.6911904761904762,
            0.5549093397194663,
            0.5339563862928349,
            0.5983701979045402,
            0.594488188976378,
            0.5555555555555556,
            0.40828402366863903,
            0.2608695652173913,
            0.5555555555555556,
            0.1
        ]
    ],
    "rho_0.09000000000000001_beta_0.001": [
        [
            11.0,
            4.7272727272727275,
            4.269230769230769,
            2.855855855855856,
            2.310725552050473,
            1.8552901023890784,
            1.5746872700515084,
            1.3615330684739426,
            1.261324639670556,
            1.1668935475088484,
            1.095943110282117,
            1.04261909848323,
            0.9699456354497897,
            0.8997978938410808,
            0.8146428571428571,
            0.7296742001761081,
            0.668216740800647,
            0.6564862413063199,
            0.6513550757923748,
            0.6962649753347427,
            0.6351758793969849,
            0.635048231511254,
            0.5848101265822785,
            0.5450643776824035,
            0.512,
            0.47540983606557374,
            0.21428571428571427,
            0.5
        ],
        [
            13.0,
            7.076923076923077,
            3.902173913043478,
            2.668523676880223,
            2.056367432150313,
            1.6918781725888326,
            1.5067506750675068,
            1.2891854212308305,
            1.2393083217538985,
            1.1713395638629283,
            1.1097691321077383,
            0.984313348089693,
            0.9204366640440598,
            0.853864218616567,
            0.7851611291531352,
            0.6878797569555485,
            0.6168376865671642,
            0.5497164461247637,
            0.46643598615916954,
            0.39317507418397624,
            0.37404580152671757,
            0.45,
            0.34782608695652173,
            0.4375,
            0.2857142857142857
        ],
        [
            13.0,
            7.230769230769231,
            3.6702127659574466,
            2.5391304347826087,
            1.9029680365296804,
            1.674865026994601,
            1.5333094555873925,
            1.3933660359729034,
            1.233971131252098,
            1.1633596085892906,
            1.0774548863370048,
            1.024040030457957,
            0.9570701717193131,
            0.905616224648986,
            0.8019031141868512,
            0.7725721377598511,
            0.7210239870993751,
            0.7258698092031426,
            0.6557759626604434,
            0.6523809523809524,
            0.5659340659340659,
            0.5284552845528455,
            0.5840978593272171,
            0.38095238095238093,
            0.3888888888888889,
            0.5
        ],
        [
            9.0,
            4.666666666666667,
            3.9047619047619047,
            2.731707317073171,
            2.3526785714285716,
            1.9724857685009487,
            1.6642616642616643,
            1.3890173410404625,
            1.260507698709946,
            1.1824034334763949,
            1.106564245810056,
            1.0670708601743084,
            1.0494674556213017,
            0.975322617160969,
            0.9228348292341765,
            0.8712207463630613,
            0.8265811716700671,
            0.7290379523389232,
            0.6392080175996089,
            0.6007677543186181,
            0.5147435897435897,
            0.5221799746514575,
            0.5073891625615764,
            0.4236453201970443,
            0.23255813953488372,
            0.3,
            0.3333333333333333,
            0.5
        ],
        [
            13.0,
            6.384615384615385,
            3.8433734939759034,
            2.717868338557994,
            2.121107266435986,
            1.6601413811854269,
            1.4660989190959712,
            1.3462913315460232,
            1.190207468879668,
            1.1494766224703419,
            1.1034021871202917,
            1.0665344789601234,
            1.0095524867614993,
            0.9148650046550119,
            0.8235094467699966,
            0.718284611141754,
            0.6735441573467027,
            0.5835482946402981,
            0.5145679012345679,
            0.5033492822966508,
            0.45977011494252873,
            0.4214876033057851,
            0.375,
            0.358974358974359,
            0.21428571428571427,
            0.6666666666666666
        ]
    ],
    "rho_0.1_beta_0.001": [
        [
            12.0,
            5.083333333333333,
            3.7540983606557377,
            2.7729257641921397,
            2.2173228346456693,
            1.8096590909090908,
            1.6428571428571428,
            1.3824653607262303,
            1.2635310392529828,
            1.2150184653262208,
            1.1487416770116239,
            1.1147508633448446,
            1.0128877433117056,
            0.8986629134412386,
            0.8249532618321361,
            0.7658938814531548,
            0.6976452119309262,
            0.64376130198915,
            0.5595744680851064,
            0.5832805573147561,
            0.4676180021953897,
            0.3427230046948357,
            0.2361111111111111,
            0.20588235294117646,
            0.14285714285714285
        ],
        [
            7.0,
            9.285714285714286,
            4.984615384615385,
            3.037037037037037,
            2.1016260162601625,
            1.683752417794971,
            1.4141298104537623,
            1.3119415109666936,
            1.2419879238272178,
            1.1659595707511854,
            1.1379088471849865,
            1.0410416076988396,
            0.959308147473828,
            0.8821967182016504,
            0.8282850059286407,
            0.7671394799054374,
            0.6837768240343348,
            0.6166666666666667,
            0.5069501226492232,
            0.5077298616761595,
            0.3494363929146538,
            0.25462962962962965,
            0.3448275862068966,
            0.35,
            0.5714285714285714,
            0.25,
            1.0
        ],
        [
            16.0,
            6.25,
            3.96,
            2.414141414141414,
            1.9811715481171548,
            1.5923970432946146,
            1.421419098143236,
            1.30284647690154,
            1.2326289398280803,
            1.1761454545454546,
            1.1728456292622442,
            1.0966306420851875,
            1.0194616576297444,
            0.9394546147978642,
            0.8684076303172498,
            0.8042502951593861,
            0.7288210248128029,
            0.6661260896006487,
            0.6055691554467564,
            0.5842185128983308,
            0.5368603642671292,
            0.5220228384991843,
            0.40822784810126583,
            0.49612403100775193,
            0.2698412698412698,
            0.35294117647058826,
            0.3333333333333333
        ],
        [
            8.0,
            8.25,
            4.257575757575758,
            2.907473309608541,
            2.1921664626682986,
            1.7900614182021217,
            1.4996880848409233,
            1.291033908882879,
            1.198936855670103,
            1.1440677966101696,
            1.1114507406536562,
            1.0804536781852874,
            0.9959764474975467,
            0.9779142319500842,
            0.8883588754694002,
            0.779243119266055,
            0.6896806623299823,
            0.6233126205271052,
            0.607870210562651,
            0.5308924485125858,
            0.48008611410118407,
            0.3431818181818182,
            0.3157894736842105,
            0.22916666666666666,
            0.1
        ],
        [
            14.0,
            5.214285714285714,
            4.575342465753424,
            2.856287425149701,
            2.10167714884696,
            1.714713216957606,
            1.4611579866162352,
            1.305638573421,
            1.2233750381446444,
            1.2011235955056179,
            1.1056036731712406,
            1.0216507516308972,
            0.9616169108103096,
            0.8752906976744186,
            0.8089066134928548,
            0.7793794618341571,
            0.7039392333509981,
            0.6507417651496102,
            0.5731424148606811,
            0.5317567567567567,
            0.44543147208121825,
            0.35714285714285715,
            0.296,
            0.2972972972972973,
            0.18181818181818182
        ]
    ]
}